LICENSE.txt
README.txt
ez_setup.py
setup.py
TGPriFlash.egg-info/PKG-INFO
TGPriFlash.egg-info/SOURCES.txt
TGPriFlash.egg-info/dependency_links.txt
TGPriFlash.egg-info/not-zip-safe
TGPriFlash.egg-info/requires.txt
TGPriFlash.egg-info/top_level.txt
tg_pri_flash/__init__.py
tg_pri_flash/flash.py