Metadata-Version: 1.0
Name: TGPriFlash
Version: 0.1.2
Summary: A TurboGears flash implementation that supports multiple priority levels.
Home-page: http://www.psychofx.com/turbogears/TGPriFlash/
Author: Chris Miles
Author-email: miles.chris@gmail.com
License: MIT
Keywords: turbogears.widgets
Platform: UNKNOWN
Classifier: Development Status :: 4 - Beta
Classifier: Operating System :: OS Independent
Classifier: Programming Language :: Python
Classifier: Topic :: Software Development :: Libraries :: Python Modules
Classifier: Framework :: TurboGears
Classifier: Framework :: TurboGears :: Widgets
